bootstraphistogram/__init__.py
bootstraphistogram/bootstrapefficiency.py
bootstraphistogram/bootstraphistogram.py
bootstraphistogram/bootstrapmoment.py
bootstraphistogram/plot.py
bootstraphistogram/py.typed
bootstraphistogram/valuewithsamples.py
bootstraphistogram-0.11.0.dist-info/LICENSE.txt
bootstraphistogram-0.11.0.dist-info/WHEEL
bootstraphistogram-0.11.0.dist-info/METADATA
bootstraphistogram-0.11.0.dist-info/RECORD
