Metadata-Version: 2.1
Name: bootstraphistogram
Version: 0.11.0
Summary: Poisson bootstrap histogram.
Home-page: https://github.com/davehadley/bootstraphistogram
License: MIT
Author: David Hadley
Author-email: davehadley@users.noreply.github.com
Requires-Python: >=3.6.2,<4.0.0
Classifier: License :: OSI Approved :: MIT License
Classifier: Programming Language :: Python :: 3
Classifier: Programming Language :: Python :: 3.10
Classifier: Programming Language :: Python :: 3.7
Classifier: Programming Language :: Python :: 3.8
Classifier: Programming Language :: Python :: 3.9
Requires-Dist: boost-histogram (>=1.0.0)
Requires-Dist: matplotlib (>=3.1,<4.0)
Requires-Dist: numpy (>=1.19.0,<1.20); python_version < "3.7"
Requires-Dist: numpy (>=1.19.0,<1.22.0); python_version >= "3.7" and python_version < "3.8"
Requires-Dist: numpy (>=1.19.0,<2.0.0); python_version >= "3.8"
Project-URL: Documentation, https://bootstraphistogram.readthedocs.io/
Project-URL: Repository, https://pypi.org/project/bootstraphistogram/
